odoo/addons/account_move_delivery_invoice/README.rst
odoo/addons/account_move_delivery_invoice/__init__.py
odoo/addons/account_move_delivery_invoice/__manifest__.py
odoo/addons/account_move_delivery_invoice/i18n/account_move_delivery_invoice.pot
odoo/addons/account_move_delivery_invoice/i18n/ja.po
odoo/addons/account_move_delivery_invoice/models/__init__.py
odoo/addons/account_move_delivery_invoice/models/account_move.py
odoo/addons/account_move_delivery_invoice/models/res_company.py
odoo/addons/account_move_delivery_invoice/models/res_config_settings.py
odoo/addons/account_move_delivery_invoice/readme/CONFIGURE.md
odoo/addons/account_move_delivery_invoice/readme/CONTEXT.md
odoo/addons/account_move_delivery_invoice/readme/CONTRIBUTORS.md
odoo/addons/account_move_delivery_invoice/readme/DESCRIPTION.md
odoo/addons/account_move_delivery_invoice/report/report_delivery_note.xml
odoo/addons/account_move_delivery_invoice/report/report_delivery_note_template.xml
odoo/addons/account_move_delivery_invoice/report/report_invoice_document.xml
odoo/addons/account_move_delivery_invoice/static/description/icon.png
odoo/addons/account_move_delivery_invoice/static/description/index.html
odoo/addons/account_move_delivery_invoice/tests/__init__.py
odoo/addons/account_move_delivery_invoice/tests/test_account_move_delivery_invoice.py
odoo/addons/account_move_delivery_invoice/views/account_move_views.xml
odoo/addons/account_move_delivery_invoice/views/res_config_settings_views.xml
odoo_addon_account_move_delivery_invoice-18.0.1.2.0.dist-info/METADATA
odoo_addon_account_move_delivery_invoice-18.0.1.2.0.dist-info/WHEEL
odoo_addon_account_move_delivery_invoice-18.0.1.2.0.dist-info/top_level.txt
odoo_addon_account_move_delivery_invoice-18.0.1.2.0.dist-info/RECORD
