Metadata-Version: 2.1
Name: odoo-addon-account_move_delivery_invoice
Version: 18.0.1.2.0
Requires-Python: >=3.10
Requires-Dist: odoo==18.0.*
Summary: Account Move Delivery Invoice
Home-page: https://github.com/OCA/l10n-japan
License: AGPL-3
Author: Quartile, Odoo Community Association (OCA)
Author-email: support@odoo-community.org
Classifier: Programming Language :: Python
Classifier: Framework :: Odoo
Classifier: Framework :: Odoo :: 18.0
Classifier: License :: OSI Approved :: GNU Affero General Public License v3
